pyeasyscrap/__init__.py
pyeasyscrap/basic_functions.py
pyeasyscrap/web_scraping_functions.py
pyeasyscrape/__init__.py
pyeasyscrape/basic_functions.py
pyeasyscrape/web_scraping_functions.py
py_easy_scrape-0.1.6.1.dist-info/LICENSE
py_easy_scrape-0.1.6.1.dist-info/METADATA
py_easy_scrape-0.1.6.1.dist-info/WHEEL
py_easy_scrape-0.1.6.1.dist-info/top_level.txt
py_easy_scrape-0.1.6.1.dist-info/RECORD
