Metadata-Version: 2.1
Name: py-easy-scrape
Version: 0.1.6.1
Summary: A useful package for web scraping with Selenium
Home-page: https://github.com/ygalvao/py-easy-scrape
Author: Yuri Henrique Galvao
Author-email: Yuri Henrique Galvao <yuri@galvao.ca>
Project-URL: Homepage, https://github.com/ygalvao/py-easy-scrape
Project-URL: Bug Tracker, https://github.com/ygalvao/py-easy-scrape/issues
Classifier: Programming Language :: Python :: 3
Classifier: License :: OSI Approved :: MIT License
Classifier: Operating System :: OS Independent
Requires-Python: >=3.7
License-File: LICENSE
Requires-Dist: selenium
